domain_utils/__init__.py
domain_utils/domain_utils.py
domain_utils-0.7.1.dist-info/LICENSE
domain_utils-0.7.1.dist-info/METADATA
domain_utils-0.7.1.dist-info/WHEEL
domain_utils-0.7.1.dist-info/top_level.txt
domain_utils-0.7.1.dist-info/RECORD
