Metadata-Version: 2.1
Name: domain-utils
Version: 0.7.1
Summary: A collection of util functions for extracting domains from urls.
Home-page: https://github.com/mozilla/domain_utils
Author: Sarah Bird
Author-email: sbird@mozilla.com
License: MPL 2.0
Keywords: domain_utils
Platform: UNKNOWN
Classifier: Development Status :: 2 - Pre-Alpha
Classifier: Intended Audience :: Developers
Classifier: License :: OSI Approved :: Mozilla Public License 2.0 (MPL 2.0)
Classifier: Natural Language :: English
Classifier: Programming Language :: Python :: 3
Classifier: Programming Language :: Python :: 3.6
Classifier: Programming Language :: Python :: 3.7
Classifier: Programming Language :: Python :: 3.8
Requires-Python: >=3.6
Requires-Dist: tldextract (==2.2.2)
